[
	{
		"month": "2017-6",
		"id": 1,
		"name": "1号加油机",
		"count": 3450,
		"time": "86.79",
		"loss": "17.358",
		"save": 21.6975,
		"reduce": "0.00434"
	}, {
		"month": "2017-6",
		"id": 2,
		"name": "2号加油机",
		"count": 3330,
		"time": "86.54",
		"loss": "17.308",
		"save": 21.635,
		"reduce": "0.00433"
	}, {
		"month": "2017-6",
		"id": 3,
		"name": "3号加油机",
		"count": 3750,
		"time": "120.86",
		"loss": "24.172",
		"save": 30.215,
		"reduce": "0.00604"
	}, {
		"month": "2017-6",
		"id": 4,
		"name": "4号加油机",
		"count": 3300,
		"time": "105.37",
		"loss": "21.074",
		"save": 26.3425,
		"reduce": "0.00527"
	}, {
		"month": "2017-6",
		"id": 5,
		"name": "1号空调",
		"count": 3240,
		"time": "82.24",
		"loss": "16.448",
		"save": 20.56,
		"reduce": "0.00411"
	}, {
		"month": "2017-6",
		"id": 6,
		"name": "2号空调",
		"count": 3870,
		"time": "125.64",
		"loss": "25.128",
		"save": 31.41,
		"reduce": "0.00628"
	}, {
		"month": "2017-7",
		"id": 1,
		"name": "1号加油机",
		"count": 3131,
		"time": "102.56",
		"loss": "20.512",
		"save": 25.64,
		"reduce": "0.00513"
	}, {
		"month": "2017-7",
		"id": 2,
		"name": "2号加油机",
		"count": 3255,
		"time": "95.62",
		"loss": "19.124",
		"save": 23.905,
		"reduce": "0.00478"
	}, {
		"month": "2017-7",
		"id": 3,
		"name": "3号加油机",
		"count": 3720,
		"time": "110.80",
		"loss": "22.160",
		"save": 27.7,
		"reduce": "0.00554"
	}, {
		"month": "2017-7",
		"id": 4,
		"name": "4号加油机",
		"count": 3968,
		"time": "104.53",
		"loss": "20.906",
		"save": 26.1325,
		"reduce": "0.00523"
	}, {
		"month": "2017-7",
		"id": 5,
		"name": "1号空调",
		"count": 3193,
		"time": "98.44",
		"loss": "19.688",
		"save": 24.61,
		"reduce": "0.00492"
	}, {
		"month": "2017-7",
		"id": 6,
		"name": "2号空调",
		"count": 3224,
		"time": "96.85",
		"loss": "19.370",
		"save": 24.2125,
		"reduce": "0.00484"
	}, {
		"month": "2017-8",
		"id": 1,
		"name": "1号加油机",
		"count": 3875,
		"time": "110.86",
		"loss": "22.172",
		"save": 27.715,
		"reduce": "0.00554"
	}, {
		"month": "2017-8",
		"id": 2,
		"name": "2号加油机",
		"count": 3999,
		"time": "125.13",
		"loss": "25.026",
		"save": 31.2825,
		"reduce": "0.00626"
	}, {
		"month": "2017-8",
		"id": 3,
		"name": "3号加油机",
		"count": 3348,
		"time": "108.74",
		"loss": "21.748",
		"save": 27.185,
		"reduce": "0.00544"
	}, {
		"month": "2017-8",
		"id": 4,
		"name": "4号加油机",
		"count": 3782,
		"time": "122.15",
		"loss": "24.430",
		"save": 30.5375,
		"reduce": "0.00611"
	}, {
		"month": "2017-8",
		"id": 5,
		"name": "1号空调",
		"count": 3286,
		"time": "91.54",
		"loss": "18.308",
		"save": 22.885,
		"reduce": "0.00458"
	}, {
		"month": "2017-8",
		"id": 6,
		"name": "2号空调",
		"count": 3596,
		"time": "111.44",
		"loss": "22.288",
		"save": 27.86,
		"reduce": "0.00557"
	}, {
		"month": "2017-9",
		"id": 1,
		"name": "1号加油机",
		"count": 3900,
		"time": "126.62",
		"loss": "25.324",
		"save": 31.655,
		"reduce": "0.00633"
	}, {
		"month": "2017-9",
		"id": 2,
		"name": "2号加油机",
		"count": 3450,
		"time": "87.95",
		"loss": "17.590",
		"save": 21.9875,
		"reduce": "0.00440"
	}, {
		"month": "2017-9",
		"id": 3,
		"name": "3号加油机",
		"count": 3900,
		"time": "110.98",
		"loss": "22.196",
		"save": 27.745,
		"reduce": "0.00555"
	}, {
		"month": "2017-9",
		"id": 4,
		"name": "4号加油机",
		"count": 3450,
		"time": "97.51",
		"loss": "19.502",
		"save": 24.3775,
		"reduce": "0.00488"
	}, {
		"month": "2017-9",
		"id": 5,
		"name": "1号空调",
		"count": 3870,
		"time": "112.75",
		"loss": "22.550",
		"save": 28.1875,
		"reduce": "0.00564"
	}, {
		"month": "2017-9",
		"id": 6,
		"name": "2号空调",
		"count": 3300,
		"time": "96.93",
		"loss": "19.386",
		"save": 24.2325,
		"reduce": "0.00485"
	}, {
		"month": "2017-10",
		"id": 1,
		"name": "1号加油机",
		"count": 3441,
		"time": "97.33",
		"loss": "19.466",
		"save": 24.3325,
		"reduce": "0.00487"
	}, {
		"month": "2017-10",
		"id": 2,
		"name": "2号加油机",
		"count": 3503,
		"time": "91.94",
		"loss": "18.388",
		"save": 22.985,
		"reduce": "0.00460"
	}, {
		"month": "2017-10",
		"id": 3,
		"name": "3号加油机",
		"count": 3162,
		"time": "102.70",
		"loss": "20.540",
		"save": 25.675,
		"reduce": "0.00513"
	}, {
		"month": "2017-10",
		"id": 4,
		"name": "4号加油机",
		"count": 3317,
		"time": "92.85",
		"loss": "18.570",
		"save": 23.2125,
		"reduce": "0.00464"
	}, {
		"month": "2017-10",
		"id": 5,
		"name": "1号空调",
		"count": 3317,
		"time": "101.33",
		"loss": "20.266",
		"save": 25.3325,
		"reduce": "0.00507"
	}, {
		"month": "2017-10",
		"id": 6,
		"name": "2号空调",
		"count": 3658,
		"time": "100.70",
		"loss": "20.140",
		"save": 25.175,
		"reduce": "0.00504"
	}, {
		"month": "2017-11",
		"id": 1,
		"name": "1号加油机",
		"count": 3720,
		"time": "121.65",
		"loss": "24.330",
		"save": 30.4125,
		"reduce": "0.00608"
	}, {
		"month": "2017-11",
		"id": 2,
		"name": "2号加油机",
		"count": 3720,
		"time": "118.55",
		"loss": "23.710",
		"save": 29.6375,
		"reduce": "0.00593"
	}, {
		"month": "2017-11",
		"id": 3,
		"name": "3号加油机",
		"count": 3360,
		"time": "86.08",
		"loss": "17.216",
		"save": 21.52,
		"reduce": "0.00430"
	}, {
		"month": "2017-11",
		"id": 4,
		"name": "4号加油机",
		"count": 3750,
		"time": "109.59",
		"loss": "21.918",
		"save": 27.3975,
		"reduce": "0.00548"
	}, {
		"month": "2017-11",
		"id": 5,
		"name": "1号空调",
		"count": 3420,
		"time": "107.31",
		"loss": "21.462",
		"save": 26.8275,
		"reduce": "0.00537"
	}, {
		"month": "2017-11",
		"id": 6,
		"name": "2号空调",
		"count": 3870,
		"time": "108.07",
		"loss": "21.614",
		"save": 27.0175,
		"reduce": "0.00540"
	}, {
		"month": "2017-12",
		"id": 1,
		"name": "1号加油机",
		"count": 3472,
		"time": "108.68",
		"loss": "21.736",
		"save": 27.17,
		"reduce": "0.00543"
	}, {
		"month": "2017-12",
		"id": 2,
		"name": "2号加油机",
		"count": 3348,
		"time": "111.02",
		"loss": "22.204",
		"save": 27.755,
		"reduce": "0.00555"
	}, {
		"month": "2017-12",
		"id": 3,
		"name": "3号加油机",
		"count": 3348,
		"time": "89.09",
		"loss": "17.818",
		"save": 22.2725,
		"reduce": "0.00445"
	}, {
		"month": "2017-12",
		"id": 4,
		"name": "4号加油机",
		"count": 3813,
		"time": "112.18",
		"loss": "22.436",
		"save": 28.045,
		"reduce": "0.00561"
	}, {
		"month": "2017-12",
		"id": 5,
		"name": "1号空调",
		"count": 3472,
		"time": "95.37",
		"loss": "19.074",
		"save": 23.8425,
		"reduce": "0.00477"
	}, {
		"month": "2017-12",
		"id": 6,
		"name": "2号空调",
		"count": 3255,
		"time": "100.20",
		"loss": "20.040",
		"save": 25.05,
		"reduce": "0.00501"
	}, {
		"month": "2018-1",
		"id": 1,
		"name": "1号加油机",
		"count": 3224,
		"time": "93.23",
		"loss": "18.646",
		"save": 23.3075,
		"reduce": "0.00466"
	}, {
		"month": "2018-1",
		"id": 2,
		"name": "2号加油机",
		"count": 3751,
		"time": "99.87",
		"loss": "19.974",
		"save": 24.9675,
		"reduce": "0.00499"
	}, {
		"month": "2018-1",
		"id": 3,
		"name": "3号加油机",
		"count": 3999,
		"time": "111.61",
		"loss": "22.322",
		"save": 27.9025,
		"reduce": "0.00558"
	}, {
		"month": "2018-1",
		"id": 4,
		"name": "4号加油机",
		"count": 3720,
		"time": "122.47",
		"loss": "24.494",
		"save": 30.6175,
		"reduce": "0.00612"
	}, {
		"month": "2018-1",
		"id": 5,
		"name": "1号空调",
		"count": 3906,
		"time": "115.82",
		"loss": "23.164",
		"save": 28.955,
		"reduce": "0.00579"
	}, {
		"month": "2018-1",
		"id": 6,
		"name": "2号空调",
		"count": 3472,
		"time": "94.88",
		"loss": "18.976",
		"save": 23.72,
		"reduce": "0.00474"
	}, {
		"month": "2018-2",
		"id": 1,
		"name": "1号加油机",
		"count": 3024,
		"time": "80.92",
		"loss": "16.184",
		"save": 20.23,
		"reduce": "0.00405"
	}, {
		"month": "2018-2",
		"id": 2,
		"name": "2号加油机",
		"count": 3388,
		"time": "91.96",
		"loss": "18.392",
		"save": 22.99,
		"reduce": "0.00460"
	}, {
		"month": "2018-2",
		"id": 3,
		"name": "3号加油机",
		"count": 2828,
		"time": "74.81",
		"loss": "14.962",
		"save": 18.7025,
		"reduce": "0.00374"
	}, {
		"month": "2018-2",
		"id": 4,
		"name": "4号加油机",
		"count": 2968,
		"time": "81.12",
		"loss": "16.224",
		"save": 20.28,
		"reduce": "0.00406"
	}, {
		"month": "2018-2",
		"id": 5,
		"name": "1号空调",
		"count": 3444,
		"time": "113.51",
		"loss": "22.702",
		"save": 28.3775,
		"reduce": "0.00568"
	}, {
		"month": "2018-2",
		"id": 6,
		"name": "2号空调",
		"count": 3164,
		"time": "102.14",
		"loss": "20.428",
		"save": 25.535,
		"reduce": "0.00511"
	}, {
		"month": "2018-3",
		"id": 1,
		"name": "1号加油机",
		"count": 3348,
		"time": "97.33",
		"loss": "19.466",
		"save": 24.3325,
		"reduce": "0.00487"
	}, {
		"month": "2018-3",
		"id": 2,
		"name": "2号加油机",
		"count": 3286,
		"time": "103.56",
		"loss": "20.712",
		"save": 25.89,
		"reduce": "0.00518"
	}, {
		"month": "2018-3",
		"id": 3,
		"name": "3号加油机",
		"count": 3410,
		"time": "110.22",
		"loss": "22.044",
		"save": 27.555,
		"reduce": "0.00551"
	}, {
		"month": "2018-3",
		"id": 4,
		"name": "4号加油机",
		"count": 3503,
		"time": "102.92",
		"loss": "20.584",
		"save": 25.73,
		"reduce": "0.00515"
	}, {
		"month": "2018-3",
		"id": 5,
		"name": "1号空调",
		"count": 3720,
		"time": "93.16",
		"loss": "18.632",
		"save": 23.29,
		"reduce": "0.00466"
	}, {
		"month": "2018-3",
		"id": 6,
		"name": "2号空调",
		"count": 3534,
		"time": "107.64",
		"loss": "21.528",
		"save": 26.91,
		"reduce": "0.00538"
	}, {
		"month": "2018-4",
		"id": 1,
		"name": "1号加油机",
		"count": 3750,
		"time": "97.12",
		"loss": "19.424",
		"save": 24.28,
		"reduce": "0.00486"
	}, {
		"month": "2018-4",
		"id": 2,
		"name": "2号加油机",
		"count": 3480,
		"time": "98.84",
		"loss": "19.768",
		"save": 24.71,
		"reduce": "0.00494"
	}, {
		"month": "2018-4",
		"id": 3,
		"name": "3号加油机",
		"count": 3840,
		"time": "123.48",
		"loss": "24.696",
		"save": 30.87,
		"reduce": "0.00617"
	}, {
		"month": "2018-4",
		"id": 4,
		"name": "4号加油机",
		"count": 3120,
		"time": "87.31",
		"loss": "17.462",
		"save": 21.8275,
		"reduce": "0.00437"
	}, {
		"month": "2018-4",
		"id": 5,
		"name": "1号空调",
		"count": 3000,
		"time": "78.52",
		"loss": "15.704",
		"save": 19.63,
		"reduce": "0.00393"
	}, {
		"month": "2018-4",
		"id": 6,
		"name": "2号空调",
		"count": 3810,
		"time": "109.82",
		"loss": "21.964",
		"save": 27.455,
		"reduce": "0.00549"
	}, {
		"month": "2018-5",
		"id": 1,
		"name": "1号加油机",
		"count": 3720,
		"time": "113.05",
		"loss": "22.610",
		"save": 28.2625,
		"reduce": "0.00565"
	}, {
		"month": "2018-5",
		"id": 2,
		"name": "2号加油机",
		"count": 3875,
		"time": "102.29",
		"loss": "20.458",
		"save": 25.5725,
		"reduce": "0.00511"
	}, {
		"month": "2018-5",
		"id": 3,
		"name": "3号加油机",
		"count": 3193,
		"time": "96.84",
		"loss": "19.368",
		"save": 24.21,
		"reduce": "0.00484"
	}, {
		"month": "2018-5",
		"id": 4,
		"name": "4号加油机",
		"count": 3441,
		"time": "90.10",
		"loss": "18.020",
		"save": 22.525,
		"reduce": "0.00450"
	}, {
		"month": "2018-5",
		"id": 5,
		"name": "1号空调",
		"count": 3906,
		"time": "101.78",
		"loss": "20.356",
		"save": 25.445,
		"reduce": "0.00509"
	}, {
		"month": "2018-5",
		"id": 6,
		"name": "2号空调",
		"count": 3286,
		"time": "91.46",
		"loss": "18.292",
		"save": 22.865,
		"reduce": "0.00457"
	}
]